[
  {
    "name": "offset",
    "dx": 0.04,
    "dy": -0.04,
    "radius_scale": 1.0,
    "aa_scale": 1.0,
    "opacity_scale": 1.0,
    "flow_scale": 1.0,
    "max": 8,
    "mean": 0.027844,
    "visible_px": 312,
    "diff_px": 846
  },
  {
    "name": "offset",
    "dx": 0.04,
    "dy": -0.02,
    "radius_scale": 1.0,
    "aa_scale": 1.0,
    "opacity_scale": 1.0,
    "flow_scale": 1.0,
    "max": 9,
    "mean": 0.02925,
    "visible_px": 296,
    "diff_px": 860
  },
  {
    "name": "offset",
    "dx": 0.08,
    "dy": -0.04,
    "radius_scale": 1.0,
    "aa_scale": 1.0,
    "opacity_scale": 1.0,
    "flow_scale": 1.0,
    "max": 7,
    "mean": 0.029362,
    "visible_px": 371,
    "diff_px": 808
  },
  {
    "name": "offset",
    "dx": 0.02,
    "dy": -0.02,
    "radius_scale": 1.0,
    "aa_scale": 1.0,
    "opacity_scale": 1.0,
    "flow_scale": 1.0,
    "max": 10,
    "mean": 0.030056,
    "visible_px": 264,
    "diff_px": 857
  },
  {
    "name": "offset",
    "dx": 0.08,
    "dy": -0.08,
    "radius_scale": 1.0,
    "aa_scale": 1.0,
    "opacity_scale": 1.0,
    "flow_scale": 1.0,
    "max": 7,
    "mean": 0.030994,
    "visible_px": 403,
    "diff_px": 870
  },
  {
    "name": "offset",
    "dx": 0,
    "dy": 0,
    "radius_scale": 1.0,
    "aa_scale": 1.0,
    "opacity_scale": 1.0,
    "flow_scale": 1.0,
    "max": 12,
    "mean": 0.035175,
    "visible_px": 274,
    "diff_px": 926
  },
  {
    "name": "radius",
    "dx": 0.0,
    "dy": 0.0,
    "radius_scale": 1.0,
    "aa_scale": 1.0,
    "opacity_scale": 1.0,
    "flow_scale": 1.0,
    "max": 12,
    "mean": 0.035175,
    "visible_px": 274,
    "diff_px": 926
  },
  {
    "name": "aa",
    "dx": 0.0,
    "dy": 0.0,
    "radius_scale": 1.0,
    "aa_scale": 1.0,
    "opacity_scale": 1.0,
    "flow_scale": 1.0,
    "max": 12,
    "mean": 0.035175,
    "visible_px": 274,
    "diff_px": 926
  },
  {
    "name": "opacity",
    "dx": 0.0,
    "dy": 0.0,
    "radius_scale": 1.0,
    "aa_scale": 1.0,
    "opacity_scale": 1.0,
    "flow_scale": 1.0,
    "max": 12,
    "mean": 0.035175,
    "visible_px": 274,
    "diff_px": 926
  },
  {
    "name": "flow",
    "dx": 0.0,
    "dy": 0.0,
    "radius_scale": 1.0,
    "aa_scale": 1.0,
    "opacity_scale": 1.0,
    "flow_scale": 1.0,
    "max": 12,
    "mean": 0.035175,
    "visible_px": 274,
    "diff_px": 926
  },
  {
    "name": "flow",
    "dx": 0.0,
    "dy": 0.0,
    "radius_scale": 1.0,
    "aa_scale": 1.0,
    "opacity_scale": 1.0,
    "flow_scale": 1.002,
    "max": 12,
    "mean": 0.035175,
    "visible_px": 274,
    "diff_px": 926
  },
  {
    "name": "flow",
    "dx": 0.0,
    "dy": 0.0,
    "radius_scale": 1.0,
    "aa_scale": 1.0,
    "opacity_scale": 1.0,
    "flow_scale": 1.005,
    "max": 12,
    "mean": 0.035175,
    "visible_px": 274,
    "diff_px": 926
  },
  {
    "name": "aa",
    "dx": 0.0,
    "dy": 0.0,
    "radius_scale": 1.0,
    "aa_scale": 0.99,
    "opacity_scale": 1.0,
    "flow_scale": 1.0,
    "max": 13,
    "mean": 0.035569,
    "visible_px": 310,
    "diff_px": 968
  },
  {
    "name": "aa",
    "dx": 0.0,
    "dy": 0.0,
    "radius_scale": 1.0,
    "aa_scale": 1.005,
    "opacity_scale": 1.0,
    "flow_scale": 1.0,
    "max": 12,
    "mean": 0.036094,
    "visible_px": 292,
    "diff_px": 917
  },
  {
    "name": "flow",
    "dx": 0.0,
    "dy": 0.0,
    "radius_scale": 1.0,
    "aa_scale": 1.0,
    "opacity_scale": 1.0,
    "flow_scale": 0.998,
    "max": 12,
    "mean": 0.036769,
    "visible_px": 282,
    "diff_px": 985
  },
  {
    "name": "offset",
    "dx": 0.02,
    "dy": 0,
    "radius_scale": 1.0,
    "aa_scale": 1.0,
    "opacity_scale": 1.0,
    "flow_scale": 1.0,
    "max": 11,
    "mean": 0.038194,
    "visible_px": 420,
    "diff_px": 1004
  },
  {
    "name": "aa",
    "dx": 0.0,
    "dy": 0.0,
    "radius_scale": 1.0,
    "aa_scale": 1.01,
    "opacity_scale": 1.0,
    "flow_scale": 1.0,
    "max": 12,
    "mean": 0.038475,
    "visible_px": 334,
    "diff_px": 945
  },
  {
    "name": "aa",
    "dx": 0.0,
    "dy": 0.0,
    "radius_scale": 1.0,
    "aa_scale": 0.98,
    "opacity_scale": 1.0,
    "flow_scale": 1.0,
    "max": 14,
    "mean": 0.040575,
    "visible_px": 439,
    "diff_px": 1101
  },
  {
    "name": "offset",
    "dx": 0.02,
    "dy": -0.04,
    "radius_scale": 1.0,
    "aa_scale": 1.0,
    "opacity_scale": 1.0,
    "flow_scale": 1.0,
    "max": 9,
    "mean": 0.041944,
    "visible_px": 547,
    "diff_px": 1025
  },
  {
    "name": "flow",
    "dx": 0.0,
    "dy": 0.0,
    "radius_scale": 1.0,
    "aa_scale": 1.0,
    "opacity_scale": 1.0,
    "flow_scale": 0.995,
    "max": 12,
    "mean": 0.0426,
    "visible_px": 291,
    "diff_px": 1264
  },
  {
    "name": "offset",
    "dx": 0,
    "dy": -0.02,
    "radius_scale": 1.0,
    "aa_scale": 1.0,
    "opacity_scale": 1.0,
    "flow_scale": 1.0,
    "max": 11,
    "mean": 0.0435,
    "visible_px": 512,
    "diff_px": 1072
  },
  {
    "name": "offset",
    "dx": -0.02,
    "dy": 0.02,
    "radius_scale": 1.0,
    "aa_scale": 1.0,
    "opacity_scale": 1.0,
    "flow_scale": 1.0,
    "max": 14,
    "mean": 0.043856,
    "visible_px": 397,
    "diff_px": 1036
  },
  {
    "name": "aa",
    "dx": 0.0,
    "dy": 0.0,
    "radius_scale": 1.0,
    "aa_scale": 1.02,
    "opacity_scale": 1.0,
    "flow_scale": 1.0,
    "max": 14,
    "mean": 0.044812,
    "visible_px": 460,
    "diff_px": 1012
  },
  {
    "name": "offset",
    "dx": -0.02,
    "dy": 0,
    "radius_scale": 1.0,
    "aa_scale": 1.0,
    "opacity_scale": 1.0,
    "flow_scale": 1.0,
    "max": 14,
    "mean": 0.045788,
    "visible_px": 470,
    "diff_px": 1079
  },
  {
    "name": "offset",
    "dx": 0.04,
    "dy": 0,
    "radius_scale": 1.0,
    "aa_scale": 1.0,
    "opacity_scale": 1.0,
    "flow_scale": 1.0,
    "max": 10,
    "mean": 0.048712,
    "visible_px": 624,
    "diff_px": 1097
  },
  {
    "name": "offset",
    "dx": 0,
    "dy": 0.02,
    "radius_scale": 1.0,
    "aa_scale": 1.0,
    "opacity_scale": 1.0,
    "flow_scale": 1.0,
    "max": 13,
    "mean": 0.048956,
    "visible_px": 546,
    "diff_px": 1129
  },
  {
    "name": "opacity",
    "dx": 0.0,
    "dy": 0.0,
    "radius_scale": 1.0,
    "aa_scale": 1.0,
    "opacity_scale": 0.998,
    "flow_scale": 1.0,
    "max": 12,
    "mean": 0.050006,
    "visible_px": 270,
    "diff_px": 1698
  },
  {
    "name": "offset",
    "dx": -0.04,
    "dy": 0.02,
    "radius_scale": 1.0,
    "aa_scale": 1.0,
    "opacity_scale": 1.0,
    "flow_scale": 1.0,
    "max": 16,
    "mean": 0.050362,
    "visible_px": 489,
    "diff_px": 1105
  },
  {
    "name": "offset",
    "dx": 0.08,
    "dy": -0.02,
    "radius_scale": 1.0,
    "aa_scale": 1.0,
    "opacity_scale": 1.0,
    "flow_scale": 1.0,
    "max": 9,
    "mean": 0.051544,
    "visible_px": 683,
    "diff_px": 1057
  },
  {
    "name": "offset",
    "dx": -0.04,
    "dy": 0.04,
    "radius_scale": 1.0,
    "aa_scale": 1.0,
    "opacity_scale": 1.0,
    "flow_scale": 1.0,
    "max": 17,
    "mean": 0.054694,
    "visible_px": 535,
    "diff_px": 1175
  },
  {
    "name": "opacity",
    "dx": 0.0,
    "dy": 0.0,
    "radius_scale": 1.0,
    "aa_scale": 1.0,
    "opacity_scale": 1.002,
    "flow_scale": 1.0,
    "max": 12,
    "mean": 0.059119,
    "visible_px": 322,
    "diff_px": 2169
  },
  {
    "name": "offset",
    "dx": 0.02,
    "dy": 0.02,
    "radius_scale": 1.0,
    "aa_scale": 1.0,
    "opacity_scale": 1.0,
    "flow_scale": 1.0,
    "max": 12,
    "mean": 0.059231,
    "visible_px": 715,
    "diff_px": 1178
  },
  {
    "name": "offset",
    "dx": 0,
    "dy": -0.04,
    "radius_scale": 1.0,
    "aa_scale": 1.0,
    "opacity_scale": 1.0,
    "flow_scale": 1.0,
    "max": 11,
    "mean": 0.059269,
    "visible_px": 732,
    "diff_px": 1144
  },
  {
    "name": "offset",
    "dx": -0.02,
    "dy": 0.04,
    "radius_scale": 1.0,
    "aa_scale": 1.0,
    "opacity_scale": 1.0,
    "flow_scale": 1.0,
    "max": 15,
    "mean": 0.059625,
    "visible_px": 659,
    "diff_px": 1203
  },
  {
    "name": "offset",
    "dx": 0.04,
    "dy": -0.08,
    "radius_scale": 1.0,
    "aa_scale": 1.0,
    "opacity_scale": 1.0,
    "flow_scale": 1.0,
    "max": 10,
    "mean": 0.059963,
    "visible_px": 709,
    "diff_px": 1092
  },
  {
    "name": "offset",
    "dx": -0.02,
    "dy": -0.02,
    "radius_scale": 1.0,
    "aa_scale": 1.0,
    "opacity_scale": 1.0,
    "flow_scale": 1.0,
    "max": 13,
    "mean": 0.060019,
    "visible_px": 721,
    "diff_px": 1172
  },
  {
    "name": "offset",
    "dx": -0.04,
    "dy": 0,
    "radius_scale": 1.0,
    "aa_scale": 1.0,
    "opacity_scale": 1.0,
    "flow_scale": 1.0,
    "max": 16,
    "mean": 0.061331,
    "visible_px": 702,
    "diff_px": 1196
  },
  {
    "name": "offset",
    "dx": -0.08,
    "dy": 0.04,
    "radius_scale": 1.0,
    "aa_scale": 1.0,
    "opacity_scale": 1.0,
    "flow_scale": 1.0,
    "max": 20,
    "mean": 0.067369,
    "visible_px": 672,
    "diff_px": 1202
  },
  {
    "name": "offset",
    "dx": 0,
    "dy": 0.04,
    "radius_scale": 1.0,
    "aa_scale": 1.0,
    "opacity_scale": 1.0,
    "flow_scale": 1.0,
    "max": 14,
    "mean": 0.068738,
    "visible_px": 762,
    "diff_px": 1225
  },
  {
    "name": "offset",
    "dx": 0.04,
    "dy": 0.02,
    "radius_scale": 1.0,
    "aa_scale": 1.0,
    "opacity_scale": 1.0,
    "flow_scale": 1.0,
    "max": 11,
    "mean": 0.070763,
    "visible_px": 801,
    "diff_px": 1188
  },
  {
    "name": "offset",
    "dx": 0.08,
    "dy": 0,
    "radius_scale": 1.0,
    "aa_scale": 1.0,
    "opacity_scale": 1.0,
    "flow_scale": 1.0,
    "max": 12,
    "mean": 0.074119,
    "visible_px": 819,
    "diff_px": 1170
  },
  {
    "name": "offset",
    "dx": -0.02,
    "dy": -0.04,
    "radius_scale": 1.0,
    "aa_scale": 1.0,
    "opacity_scale": 1.0,
    "flow_scale": 1.0,
    "max": 13,
    "mean": 0.076369,
    "visible_px": 814,
    "diff_px": 1217
  },
  {
    "name": "offset",
    "dx": -0.08,
    "dy": 0.08,
    "radius_scale": 1.0,
    "aa_scale": 1.0,
    "opacity_scale": 1.0,
    "flow_scale": 1.0,
    "max": 22,
    "mean": 0.076912,
    "visible_px": 782,
    "diff_px": 1300
  },
  {
    "name": "offset",
    "dx": -0.04,
    "dy": -0.02,
    "radius_scale": 1.0,
    "aa_scale": 1.0,
    "opacity_scale": 1.0,
    "flow_scale": 1.0,
    "max": 16,
    "mean": 0.076931,
    "visible_px": 817,
    "diff_px": 1244
  },
  {
    "name": "offset",
    "dx": 0.02,
    "dy": -0.08,
    "radius_scale": 1.0,
    "aa_scale": 1.0,
    "opacity_scale": 1.0,
    "flow_scale": 1.0,
    "max": 12,
    "mean": 0.077662,
    "visible_px": 813,
    "diff_px": 1173
  },
  {
    "name": "offset",
    "dx": -0.08,
    "dy": 0.02,
    "radius_scale": 1.0,
    "aa_scale": 1.0,
    "opacity_scale": 1.0,
    "flow_scale": 1.0,
    "max": 20,
    "mean": 0.079219,
    "visible_px": 812,
    "diff_px": 1276
  },
  {
    "name": "opacity",
    "dx": 0.0,
    "dy": 0.0,
    "radius_scale": 1.0,
    "aa_scale": 1.0,
    "opacity_scale": 0.995,
    "flow_scale": 1.0,
    "max": 12,
    "mean": 0.080194,
    "visible_px": 707,
    "diff_px": 2813
  },
  {
    "name": "offset",
    "dx": 0.02,
    "dy": 0.04,
    "radius_scale": 1.0,
    "aa_scale": 1.0,
    "opacity_scale": 1.0,
    "flow_scale": 1.0,
    "max": 13,
    "mean": 0.080325,
    "visible_px": 841,
    "diff_px": 1245
  },
  {
    "name": "radius",
    "dx": 0.0,
    "dy": 0.0,
    "radius_scale": 1.005,
    "aa_scale": 1.0,
    "opacity_scale": 1.0,
    "flow_scale": 1.0,
    "max": 17,
    "mean": 0.086813,
    "visible_px": 898,
    "diff_px": 1337
  },
  {
    "name": "opacity",
    "dx": 0.0,
    "dy": 0.0,
    "radius_scale": 1.0,
    "aa_scale": 1.0,
    "opacity_scale": 1.005,
    "flow_scale": 1.0,
    "max": 13,
    "mean": 0.087563,
    "visible_px": 822,
    "diff_px": 3166
  },
  {
    "name": "radius",
    "dx": 0.0,
    "dy": 0.0,
    "radius_scale": 0.995,
    "aa_scale": 1.0,
    "opacity_scale": 1.0,
    "flow_scale": 1.0,
    "max": 15,
    "mean": 0.089775,
    "visible_px": 858,
    "diff_px": 1150
  },
  {
    "name": "offset",
    "dx": -0.04,
    "dy": 0.08,
    "radius_scale": 1.0,
    "aa_scale": 1.0,
    "opacity_scale": 1.0,
    "flow_scale": 1.0,
    "max": 19,
    "mean": 0.090356,
    "visible_px": 880,
    "diff_px": 1314
  },
  {
    "name": "offset",
    "dx": 0.04,
    "dy": 0.04,
    "radius_scale": 1.0,
    "aa_scale": 1.0,
    "opacity_scale": 1.0,
    "flow_scale": 1.0,
    "max": 13,
    "mean": 0.092813,
    "visible_px": 899,
    "diff_px": 1256
  },
  {
    "name": "offset",
    "dx": -0.04,
    "dy": -0.04,
    "radius_scale": 1.0,
    "aa_scale": 1.0,
    "opacity_scale": 1.0,
    "flow_scale": 1.0,
    "max": 15,
    "mean": 0.094219,
    "visible_px": 876,
    "diff_px": 1273
  },
  {
    "name": "offset",
    "dx": -0.08,
    "dy": 0,
    "radius_scale": 1.0,
    "aa_scale": 1.0,
    "opacity_scale": 1.0,
    "flow_scale": 1.0,
    "max": 20,
    "mean": 0.09495,
    "visible_px": 899,
    "diff_px": 1318
  },
  {
    "name": "offset",
    "dx": 0,
    "dy": -0.08,
    "radius_scale": 1.0,
    "aa_scale": 1.0,
    "opacity_scale": 1.0,
    "flow_scale": 1.0,
    "max": 14,
    "mean": 0.095569,
    "visible_px": 900,
    "diff_px": 1224
  },
  {
    "name": "offset",
    "dx": 0.08,
    "dy": 0.02,
    "radius_scale": 1.0,
    "aa_scale": 1.0,
    "opacity_scale": 1.0,
    "flow_scale": 1.0,
    "max": 14,
    "mean": 0.096619,
    "visible_px": 912,
    "diff_px": 1222
  },
  {
    "name": "offset",
    "dx": -0.02,
    "dy": 0.08,
    "radius_scale": 1.0,
    "aa_scale": 1.0,
    "opacity_scale": 1.0,
    "flow_scale": 1.0,
    "max": 17,
    "mean": 0.100631,
    "visible_px": 919,
    "diff_px": 1324
  },
  {
    "name": "offset",
    "dx": -0.08,
    "dy": -0.02,
    "radius_scale": 1.0,
    "aa_scale": 1.0,
    "opacity_scale": 1.0,
    "flow_scale": 1.0,
    "max": 20,
    "mean": 0.11175,
    "visible_px": 952,
    "diff_px": 1333
  },
  {
    "name": "offset",
    "dx": 0,
    "dy": 0.08,
    "radius_scale": 1.0,
    "aa_scale": 1.0,
    "opacity_scale": 1.0,
    "flow_scale": 1.0,
    "max": 16,
    "mean": 0.112162,
    "visible_px": 963,
    "diff_px": 1331
  },
  {
    "name": "offset",
    "dx": -0.02,
    "dy": -0.08,
    "radius_scale": 1.0,
    "aa_scale": 1.0,
    "opacity_scale": 1.0,
    "flow_scale": 1.0,
    "max": 16,
    "mean": 0.113794,
    "visible_px": 954,
    "diff_px": 1275
  },
  {
    "name": "offset",
    "dx": 0.08,
    "dy": 0.04,
    "radius_scale": 1.0,
    "aa_scale": 1.0,
    "opacity_scale": 1.0,
    "flow_scale": 1.0,
    "max": 17,
    "mean": 0.119906,
    "visible_px": 985,
    "diff_px": 1277
  },
  {
    "name": "offset",
    "dx": 0.02,
    "dy": 0.08,
    "radius_scale": 1.0,
    "aa_scale": 1.0,
    "opacity_scale": 1.0,
    "flow_scale": 1.0,
    "max": 15,
    "mean": 0.1251,
    "visible_px": 1010,
    "diff_px": 1353
  },
  {
    "name": "offset",
    "dx": -0.08,
    "dy": -0.04,
    "radius_scale": 1.0,
    "aa_scale": 1.0,
    "opacity_scale": 1.0,
    "flow_scale": 1.0,
    "max": 19,
    "mean": 0.129769,
    "visible_px": 995,
    "diff_px": 1359
  },
  {
    "name": "offset",
    "dx": -0.04,
    "dy": -0.08,
    "radius_scale": 1.0,
    "aa_scale": 1.0,
    "opacity_scale": 1.0,
    "flow_scale": 1.0,
    "max": 18,
    "mean": 0.1314,
    "visible_px": 1003,
    "diff_px": 1312
  },
  {
    "name": "offset",
    "dx": 0.04,
    "dy": 0.08,
    "radius_scale": 1.0,
    "aa_scale": 1.0,
    "opacity_scale": 1.0,
    "flow_scale": 1.0,
    "max": 16,
    "mean": 0.138431,
    "visible_px": 1042,
    "diff_px": 1349
  },
  {
    "name": "radius",
    "dx": 0.0,
    "dy": 0.0,
    "radius_scale": 1.01,
    "aa_scale": 1.0,
    "opacity_scale": 1.0,
    "flow_scale": 1.0,
    "max": 22,
    "mean": 0.156656,
    "visible_px": 1129,
    "diff_px": 1451
  },
  {
    "name": "radius",
    "dx": 0.0,
    "dy": 0.0,
    "radius_scale": 0.99,
    "aa_scale": 1.0,
    "opacity_scale": 1.0,
    "flow_scale": 1.0,
    "max": 19,
    "mean": 0.158025,
    "visible_px": 1043,
    "diff_px": 1203
  },
  {
    "name": "offset",
    "dx": 0.08,
    "dy": 0.08,
    "radius_scale": 1.0,
    "aa_scale": 1.0,
    "opacity_scale": 1.0,
    "flow_scale": 1.0,
    "max": 21,
    "mean": 0.166331,
    "visible_px": 1095,
    "diff_px": 1344
  },
  {
    "name": "offset",
    "dx": -0.08,
    "dy": -0.08,
    "radius_scale": 1.0,
    "aa_scale": 1.0,
    "opacity_scale": 1.0,
    "flow_scale": 1.0,
    "max": 22,
    "mean": 0.167738,
    "visible_px": 1086,
    "diff_px": 1368
  }
]