[
  {
    "clip": "Vector_Thickness_50.clip",
    "max": 12,
    "mean": 0.017019,
    "diff_px": 529,
    "visible_px": 318,
    "bbox_visible": [
      17,
      34,
      186,
      49
    ],
    "signed_rgba_mean_visible": [
      0.154088,
      0.509434,
      0.490566,
      0.0
    ],
    "output_darker_extra_px": 144,
    "output_lighter_missing_px": 174,
    "top_rows_count_y": [
      [
        36,
        45
      ],
      [
        35,
        35
      ],
      [
        33,
        37
      ],
      [
        31,
        44
      ],
      [
        30,
        46
      ],
      [
        29,
        36
      ],
      [
        25,
        43
      ],
      [
        25,
        38
      ],
      [
        22,
        34
      ],
      [
        12,
        48
      ],
      [
        11,
        42
      ],
      [
        8,
        47
      ]
    ],
    "top_cols_count_x": [
      [
        5,
        21
      ],
      [
        5,
        20
      ],
      [
        4,
        185
      ],
      [
        4,
        184
      ],
      [
        4,
        25
      ],
      [
        4,
        23
      ],
      [
        4,
        22
      ],
      [
        3,
        182
      ],
      [
        3,
        164
      ],
      [
        3,
        162
      ],
      [
        3,
        160
      ],
      [
        3,
        156
      ]
    ],
    "mask": "tmp_vector_probe/Vector_Thickness_50_signed_diffmask.png",
    "heat": "tmp_vector_probe/Vector_Thickness_50_heat.png"
  },
  {
    "clip": "Vector_Thickness_50_Angle_45.clip",
    "max": 35,
    "mean": 0.050444,
    "diff_px": 768,
    "visible_px": 651,
    "bbox_visible": [
      5,
      34,
      199,
      56
    ],
    "signed_rgba_mean_visible": [
      0.219662,
      0.688172,
      0.603687,
      0.0
    ],
    "output_darker_extra_px": 309,
    "output_lighter_missing_px": 342,
    "top_rows_count_y": [
      [
        66,
        40
      ],
      [
        61,
        54
      ],
      [
        58,
        38
      ],
      [
        57,
        41
      ],
      [
        52,
        55
      ],
      [
        50,
        42
      ],
      [
        49,
        39
      ],
      [
        39,
        52
      ],
      [
        38,
        51
      ],
      [
        38,
        37
      ],
      [
        26,
        36
      ],
      [
        22,
        53
      ]
    ],
    "top_cols_count_x": [
      [
        5,
        186
      ],
      [
        5,
        173
      ],
      [
        5,
        171
      ],
      [
        5,
        147
      ],
      [
        5,
        146
      ],
      [
        5,
        136
      ],
      [
        5,
        134
      ],
      [
        5,
        133
      ],
      [
        5,
        130
      ],
      [
        5,
        118
      ],
      [
        5,
        107
      ],
      [
        5,
        103
      ]
    ],
    "mask": "tmp_vector_probe/Vector_Thickness_50_Angle_45_signed_diffmask.png",
    "heat": "tmp_vector_probe/Vector_Thickness_50_Angle_45_heat.png"
  },
  {
    "clip": "Vector_Thickness_50_Angle_90.clip",
    "max": 21,
    "mean": 0.052687,
    "diff_px": 833,
    "visible_px": 725,
    "bbox_visible": [
      9,
      30,
      194,
      54
    ],
    "signed_rgba_mean_visible": [
      0.333793,
      1.097931,
      0.997241,
      0.0
    ],
    "output_darker_extra_px": 340,
    "output_lighter_missing_px": 385,
    "top_rows_count_y": [
      [
        163,
        34
      ],
      [
        134,
        51
      ],
      [
        110,
        33
      ],
      [
        108,
        35
      ],
      [
        64,
        52
      ],
      [
        62,
        50
      ],
      [
        23,
        36
      ],
      [
        18,
        32
      ],
      [
        9,
        31
      ],
      [
        8,
        48
      ],
      [
        7,
        30
      ],
      [
        6,
        47
      ]
    ],
    "top_cols_count_x": [
      [
        5,
        188
      ],
      [
        5,
        182
      ],
      [
        5,
        152
      ],
      [
        5,
        142
      ],
      [
        5,
        138
      ],
      [
        5,
        137
      ],
      [
        5,
        135
      ],
      [
        5,
        130
      ],
      [
        5,
        129
      ],
      [
        5,
        114
      ],
      [
        5,
        113
      ],
      [
        5,
        108
      ]
    ],
    "mask": "tmp_vector_probe/Vector_Thickness_50_Angle_90_signed_diffmask.png",
    "heat": "tmp_vector_probe/Vector_Thickness_50_Angle_90_heat.png"
  }
]